{"ongoing_trials": {}, "hyperparameters": {"space": [{"class_name": "Int", "config": {"name": "num_layers", "default": null, "conditions": [], "min_value": 2, "max_value": 8, "step": 1, "sampling": "linear"}}, {"class_name": "Int", "config": {"name": "units_0", "default": null, "conditions": [], "min_value": 12, "max_value": 144, "step": 12, "sampling": "linear"}}, {"class_name": "Choice", "config": {"name": "activation", "default": "relu", "conditions": [], "values": ["relu", "tanh", "sigmoid", "elu"], "ordered": false}}, {"class_name": "Int", "config": {"name": "units_1", "default": null, "conditions": [], "min_value": 12, "max_value": 144, "step": 12, "sampling": "linear"}}, {"class_name": "Boolean", "config": {"name": "dropout", "default": false, "conditions": []}}, {"class_name": "Float", "config": {"name": "learning_rate", "default": 0.0001, "conditions": [], "min_value": 0.0001, "max_value": 0.01, "step": null, "sampling": "log"}}, {"class_name": "Int", "config": {"name": "units_2", "default": null, "conditions": [], "min_value": 12, "max_value": 144, "step": 12, "sampling": "linear"}}, {"class_name": "Int", "config": {"name": "units_3", "default": null, "conditions": [], "min_value": 12, "max_value": 144, "step": 12, "sampling": "linear"}}, {"class_name": "Int", "config": {"name": "units_4", "default": null, "conditions": [], "min_value": 12, "max_value": 144, "step": 12, "sampling": "linear"}}, {"class_name": "Int", "config": {"name": "units_5", "default": null, "conditions": [], "min_value": 12, "max_value": 144, "step": 12, "sampling": "linear"}}], "values": {"num_layers": 2, "units_0": 12, "activation": "relu", "units_1": 12, "dropout": false, "learning_rate": 0.0001, "units_2": 12, "units_3": 12, "units_4": 12, "units_5": 12}}, "start_order": ["0", "1", "2"], "end_order": ["0", "1", "2"], "run_times": {"0": 1, "1": 1, "2": 1}, "retry_queue": [], "seed": 42, "seed_state": 68, "tried_so_far": ["1abc5edddc0407bdd4c8ab6266d3f552", "f6d8e79b8fe23481ddf3f2d6841a8f10", "c9645dc44b29b150dc99442097425166"], "id_to_hash": {"0": "f6d8e79b8fe23481ddf3f2d6841a8f10", "1": "c9645dc44b29b150dc99442097425166", "2": "1abc5edddc0407bdd4c8ab6266d3f552"}, "display": {"search_start": "2024-03-09T20:26:59.565560", "trial_start": {"0": "2024-03-09T20:26:59.565560", "1": "2024-03-09T20:27:01.709539", "2": "2024-03-09T20:27:03.731481"}, "trial_number": {"0": 1, "1": 2, "2": 3}}}